{
  "shipments": [
    {
      "shipper": "GUANGDONG SHANGTAI SPORTS GOODS CO., LTD",
      "hbl": "JYQDH2512361",
      "mode": "45' HC",
      "vessel": "CMA CGM NINGBO / 0TNHIN1MA",
      "poNumber": "T-857500",
      "units": 2292.0,
      "cbm": 75.6,
      "containerNumber": "TCNU5873733"
    },
    {
      "shipper": "GUANGDONG SHANGTAI SPORTS GOODS CO., LTD",
      "hbl": "JYQDH2512362",
      "mode": "45' HC",
      "vessel": "CMA CGM NINGBO / 0TNHIN1MA",
      "poNumber": "T-857500",
      "units": 2287.0,
      "cbm": 75.7,
      "containerNumber": "TIIU6280942"
    },
    {
      "shipper": "GUANGDONG SHANGTAI SPORTS GOODS CO., LTD",
      "hbl": "JYQDH2512362",
      "mode": "45' HC",
      "vessel": "CMA CGM NINGBO / 0TNHIN1MA",
      "poNumber": "T-857500",
      "units": 2219.0,
      "cbm": 73.724,
      "containerNumber": "OOLU9110752"
    },
    {
      "shipper": "CBS HOUSEWARES LIMITED",
      "hbl": "JYQDH2601001",
      "mode": "40' GP",
      "vessel": "MH PERSEUS / 0TNHKN1MA",
      "poNumber": "Z135000",
      "units": 4550.0,
      "cbm": 55.921,
      "containerNumber": "CSNU8939680"
    },
    {
      "shipper": "CBS HOUSEWARES LIMITED",
      "hbl": "JYQDH2601001",
      "mode": "40' HC",
      "vessel": "MH PERSEUS / 0TNHKN1MA",
      "poNumber": "Z135000",
      "units": 12546.0,
      "cbm": 66.222,
      "containerNumber": "OOCU9228883"
    },
    {
      "shipper": "GLORY COMMODITY (HONG KONG) LIMITED",
      "hbl": "JYQDH2512424",
      "mode": "45' HC",
      "vessel": "HYUNDAI MARS / 0052E",
      "poNumber": "2100",
      "units": 400.0,
      "cbm": 65.76,
      "containerNumber": "HDMU6994485"
    },
    {
      "shipper": "CBS HOUSEWARES LIMITED",
      "hbl": "JYQDH2601153",
      "mode": "20' GP",
      "vessel": "EVER SMILE / 0145E",
      "poNumber": "Z135000",
      "units": 8406.0,
      "cbm": 24.91,
      "containerNumber": "TRDU6540192"
    },
    {
      "shipper": "GUANGDONG SHANGTAI SPORTS GOODS CO., LTD",
      "hbl": "JYQDH2601135",
      "mode": "45' HC",
      "vessel": "MAERSK SYDNEY / 6030E",
      "poNumber": "T-857600",
      "units": 2152.0,
      "cbm": 74.74,
      "containerNumber": "MRSU4516373"
    },
    {
      "shipper": "GUANGDONG SHANGTAI SPORTS GOODS CO., LTD",
      "hbl": "JYQDH2601135",
      "mode": "45' HC",
      "vessel": "MAERSK SYDNEY / 6030E",
      "poNumber": "T-857600",
      "units": 2150.0,
      "cbm": 74.719,
      "containerNumber": "MRSU4599547"
    },
    {
      "shipper": "GLORY COMMODITY (HONG KONG) LIMITED",
      "hbl": "JYQDH2512422",
      "mode": "45' HC",
      "vessel": "ONE HAWK / 034E",
      "poNumber": "2100",
      "units": 400.0,
      "cbm": 65.76,
      "containerNumber": "MOEU1418769"
    },
    {
      "shipper": "GLORY COMMODITY (HONG KONG) LIMITED",
      "hbl": "JYQDH2601408",
      "mode": "40' HC",
      "vessel": "CMA CGM OTELLO / 0TNHRS1MA",
      "poNumber": "T-857900 / T-857800",
      "units": 20700.0,
      "cbm": 62.031,
      "containerNumber": "CSNU6840913"
    },
    {
      "shipper": "GLORY COMMODITY (HONG KONG) LIMITED",
      "hbl": "JYQDH2601408",
      "mode": "40' HC",
      "vessel": "CMA CGM OTELLO / 0TNHRS1MA",
      "poNumber": "T-857900 / T-857800",
      "units": 11210.0,
      "cbm": 52.732,
      "containerNumber": "OOCU9561826"
    },
    {
      "shipper": "GLORY COMMODITY (HONG KONG) LIMITED",
      "hbl": "JYQDH2602072",
      "mode": "40' HC",
      "vessel": "EVER SHINE / 0149-156E",
      "poNumber": "T-857700",
      "units": 1997.0,
      "cbm": 70.0,
      "containerNumber": "CSGU6529420"
    },
    {
      "shipper": "GLORY COMMODITY (HONG KONG) LIMITED",
      "hbl": "JYQDH2602072",
      "mode": "40' HC",
      "vessel": "EVER SHINE / 0149-156E",
      "poNumber": "T-857700",
      "units": 2893.0,
      "cbm": 67.2,
      "containerNumber": "CSGU6700614"
    },
    {
      "shipper": "GLORY COMMODITY (HONG KONG) LIMITED",
      "hbl": "JYQDH2602072",
      "mode": "40' HC",
      "vessel": "EVER SHINE / 0149-156E",
      "poNumber": "T-857700",
      "units": 1470.0,
      "cbm": 63.4,
      "containerNumber": "CSGU6706628"
    },
    {
      "shipper": "DGDL LONGYU MYSH",
      "hbl": "JYQDH2602119",
      "mode": "40' HQ",
      "vessel": "EVER ELITE / 0150-181E",
      "poNumber": "T-870100",
      "units": 1734.0,
      "cbm": 68.8,
      "containerNumber": "FFAU7869827"
    },
    {
      "shipper": "DGDL LONGYU MYSH",
      "hbl": "JYQDH2602151",
      "mode": "20' GP",
      "vessel": "OOCL OAKLAND / 139E",
      "poNumber": "26182T1 / \n26182U2 /\nT-870100",
      "units": 650.0,
      "cbm": 22.1,
      "containerNumber": "OOLU2290605"
    },
    {
      "shipper": "SHIPMENT STATUS SUMMARY",
      "hbl": "",
      "mode": "",
      "vessel": "",
      "poNumber": "",
      "units": 0.0,
      "cbm": null,
      "containerNumber": ""
    },
    {
      "shipper": "Status",
      "hbl": "Count",
      "mode": "Total Units",
      "vessel": "",
      "poNumber": "",
      "units": 0.0,
      "cbm": 0.0,
      "containerNumber": "Total CBM"
    },
    {
      "shipper": "Pending Shipment",
      "hbl": "3 - 2",
      "mode": "",
      "vessel": "",
      "poNumber": "",
      "units": 0.0,
      "cbm": 4.0,
      "containerNumber": ""
    },
    {
      "shipper": "In Transit",
      "hbl": "2",
      "mode": "2384",
      "vessel": "",
      "poNumber": "",
      "units": 0.0,
      "cbm": null,
      "containerNumber": "90.9"
    },
    {
      "shipper": "Delivered",
      "hbl": "15",
      "mode": "75672",
      "vessel": "",
      "poNumber": "",
      "units": 0.0,
      "cbm": null,
      "containerNumber": "968.419"
    },
    {
      "shipper": "TOTAL",
      "hbl": "17",
      "mode": "78056",
      "vessel": "",
      "poNumber": "",
      "units": 0.0,
      "cbm": null,
      "containerNumber": "1059.319"
    },
    {
      "shipper": "UPCOMING ARRIVALS (Next 30 Days)",
      "hbl": "",
      "mode": "",
      "vessel": "",
      "poNumber": "",
      "units": 0.0,
      "cbm": null,
      "containerNumber": ""
    },
    {
      "shipper": "PO#",
      "hbl": "Container",
      "mode": "Vessel",
      "vessel": "ETA Final",
      "poNumber": "Units",
      "units": 0.0,
      "cbm": 0.0,
      "containerNumber": "ETA Port"
    }
  ],
  "itemsByContainer": [
    {
      "invoice": "GL250066GGA",
      "eta": "2026-01-24",
      "poNumber": "T-857500",
      "sku": "GGRTFTG2228",
      "description": "PGA TOUR Tee Up Golf Club Set - Green",
      "containerNumber": "TCNU5873733",
      "qty": 518.0
    },
    {
      "invoice": "GL250066GGB",
      "eta": "2026-01-24",
      "poNumber": "T-857500",
      "sku": "GGRTFTG2228",
      "description": "PGA TOUR Tee Up Golf Club Set - Green",
      "containerNumber": "TIIU6280942",
      "qty": 510.0
    },
    {
      "invoice": "GL250066GGC",
      "eta": "2026-01-24",
      "poNumber": "T-857500",
      "sku": "GGRTFTG2228",
      "description": "PGA TOUR Tee Up Golf Club Set - Green",
      "containerNumber": "OOLU9110752",
      "qty": 468.0
    },
    {
      "invoice": "GL260003GGA",
      "eta": "2026-02-08",
      "poNumber": "T-857500",
      "sku": "GGRTFTG2228",
      "description": "Short Ship Makeup - Green",
      "containerNumber": "MRSU4516373",
      "qty": 54.0
    },
    {
      "invoice": "GL260002",
      "eta": "2026-01-29",
      "poNumber": "2100",
      "sku": "KIT 1 (Grades K-5)",
      "description": "First Tee Canada Kit - 300 Kits",
      "containerNumber": "HDMU6994485",
      "qty": 300.0
    },
    {
      "invoice": "GL260001",
      "eta": "2026-03-03",
      "poNumber": "2100",
      "sku": "KIT 1 (Grades K-5)",
      "description": "First Tee USA Kit - 300 Kits",
      "containerNumber": "MOEU1418769",
      "qty": 300.0
    },
    {
      "invoice": "GL260005GG",
      "eta": "2026-03-02",
      "poNumber": "T-857900",
      "sku": "GGWMSS2451BM",
      "description": "PGA TOUR Tee Up Small Golf Club Set",
      "containerNumber": "CSNU6840913",
      "qty": 3200.0
    },
    {
      "invoice": "GL260006GG",
      "eta": "2026-03-02",
      "poNumber": "T-857900",
      "sku": "GGWMSS2452BM",
      "description": "PGA TOUR Tee Up Medium Golf Club Set",
      "containerNumber": "OOCU9561826",
      "qty": 3000.0
    },
    {
      "invoice": "",
      "eta": null,
      "poNumber": "",
      "sku": "",
      "description": "",
      "containerNumber": "NON-GOLF (EGB)",
      "qty": 0.0
    },
    {
      "invoice": "C260001EGB",
      "eta": "2026-01-30",
      "poNumber": "Z135000",
      "sku": "TH-TB40HSS-AQUA",
      "description": "40oz Handle Tumbler - Aqua",
      "containerNumber": "OOCU9228883",
      "qty": 1386.0
    },
    {
      "invoice": "C260002EGB",
      "eta": "2026-01-30",
      "poNumber": "Z135000",
      "sku": "TH-TB40HSS-DSRS",
      "description": "40oz Handle Tumbler - Desert Rose",
      "containerNumber": "CSNU8939680",
      "qty": 1260.0
    }
  ],
  "lastUpload": "2026-03-11T11:17:34.082590"
}